{
    "$schema": "http://json-schema.org/draft-04/schema",
    "maxProperties": 36,
    "minProperties": 36,
    "properties": {
        "buy_currency": {
            "maxLength": 5,
            "minLength": 5,
            "type": [
                "null",
                "string"
            ]
        },
        "buy_price": {
            "exclusiveMaximum": false,
            "exclusiveMinimum": false,
            "maximum": 7000,
            "minimum": 200,
            "type": [
                "integer",
                "null"
            ]
        },
        "catalog_category": {
            "maxLength": 14,
            "minLength": 8,
            "type": [
                "string"
            ]
        },
        "category": {
            "maxLength": 25,
            "minLength": 3,
            "type": [
                "string"
            ]
        },
        "ceiling_category": {
            "maxLength": 5,
            "minLength": 4,
            "type": [
                "string"
            ]
        },
        "color_1": {
            "maxLength": 8,
            "minLength": 3,
            "type": [
                "string"
            ]
        },
        "color_2": {
            "maxLength": 8,
            "minLength": 3,
            "type": [
                "string"
            ]
        },
        "curtain_category": {
            "maxLength": 14,
            "minLength": 8,
            "type": [
                "null",
                "string"
            ]
        },
        "curtain_color": {
            "maxLength": 15,
            "minLength": 4,
            "type": [
                "null",
                "string"
            ]
        },
        "exchange_currency": {
            "maxLength": 14,
            "minLength": 4,
            "type": [
                "null",
                "string"
            ]
        },
        "exchange_price": {
            "exclusiveMaximum": false,
            "exclusiveMinimum": false,
            "maximum": 2700,
            "minimum": 12,
            "type": [
                "integer",
                "null"
            ]
        },
        "filename": {
            "maxLength": 27,
            "minLength": 14,
            "type": [
                "string"
            ]
        },
        "filename_image": {
            "maxLength": 27,
            "minLength": 14,
            "type": [
                "string"
            ]
        },
        "has_vfx": {
            "type": [
                "boolean"
            ]
        },
        "hha_category": {
            "type": [
                "null"
            ]
        },
        "hha_concept_1": {
            "maxLength": 13,
            "minLength": 3,
            "type": [
                "null",
                "string"
            ]
        },
        "hha_concept_2": {
            "maxLength": 17,
            "minLength": 3,
            "type": [
                "null",
                "string"
            ]
        },
        "hha_points": {
            "exclusiveMaximum": false,
            "exclusiveMinimum": false,
            "maximum": 573,
            "minimum": 103,
            "type": [
                "integer"
            ]
        },
        "hha_series": {
            "maxLength": 23,
            "minLength": 4,
            "type": [
                "null",
                "string"
            ]
        },
        "hha_set": {
            "type": [
                "null"
            ]
        },
        "image_url": {
            "maxLength": 66,
            "minLength": 53,
            "type": [
                "string"
            ]
        },
        "internal_id": {
            "exclusiveMaximum": false,
            "exclusiveMinimum": false,
            "maximum": 14896,
            "minimum": 4795,
            "type": [
                "integer"
            ]
        },
        "internal_label": {
            "type": [
                "null"
            ]
        },
        "internal_name": {
            "type": [
                "null"
            ]
        },
        "is_craftable": {
            "type": [
                "boolean"
            ]
        },
        "is_seasonal": {
            "type": [
                "boolean"
            ]
        },
        "is_unlocked": {
            "type": [
                "boolean"
            ]
        },
        "name": {
            "maxLength": 27,
            "minLength": 8,
            "type": [
                "string"
            ]
        },
        "pane_category": {
            "maxLength": 6,
            "minLength": 5,
            "type": [
                "null",
                "string"
            ]
        },
        "sell_currency": {
            "maxLength": 5,
            "minLength": 5,
            "type": [
                "string"
            ]
        },
        "sell_price": {
            "exclusiveMaximum": false,
            "exclusiveMinimum": false,
            "maximum": 44000,
            "minimum": 50,
            "type": [
                "integer"
            ]
        },
        "unique_entry_id": {
            "maxLength": 17,
            "minLength": 17,
            "type": [
                "string"
            ]
        },
        "version_added": {
            "maxLength": 5,
            "minLength": 5,
            "type": [
                "string"
            ]
        },
        "vfx_category": {
            "maxLength": 8,
            "minLength": 6,
            "type": [
                "null",
                "string"
            ]
        },
        "window_category": {
            "maxLength": 12,
            "minLength": 4,
            "type": [
                "null",
                "string"
            ]
        },
        "window_color": {
            "maxLength": 12,
            "minLength": 4,
            "type": [
                "null",
                "string"
            ]
        }
    },
    "required": [
        "buy_currency",
        "buy_price",
        "catalog_category",
        "category",
        "ceiling_category",
        "color_1",
        "color_2",
        "curtain_category",
        "curtain_color",
        "exchange_currency",
        "exchange_price",
        "filename",
        "filename_image",
        "has_vfx",
        "hha_category",
        "hha_concept_1",
        "hha_concept_2",
        "hha_points",
        "hha_series",
        "hha_set",
        "image_url",
        "internal_id",
        "internal_label",
        "internal_name",
        "is_craftable",
        "is_seasonal",
        "is_unlocked",
        "name",
        "pane_category",
        "sell_currency",
        "sell_price",
        "unique_entry_id",
        "version_added",
        "vfx_category",
        "window_category",
        "window_color"
    ],
    "title": "FurnitureWallpaper",
    "type": "object"
}
